coinwagon-0.1.0.dist-info/METADATA
coinwagon-0.1.0.dist-info/WHEEL
coinwagon/__init__.py
coinwagon/coinwagon.cp312-win_amd64.pyd
coinwagon-0.1.0.dist-info/RECORD
