Metadata-Version: 2.4
Name: coinwagon
Version: 0.1.0
Classifier: Programming Language :: Python :: 3
Classifier: Programming Language :: Rust
Classifier: License :: OSI Approved :: MIT License
Summary: A fast cryptocurrency CLI tool implemented in Rust
Author-email: Randy Ungaro <xrandyungarox@example.com>
License: MIT
Requires-Python: >=3.8
Project-URL: Homepage, https://github.com/randyungaro/coinwagon
Project-URL: Repository, https://github.com/randyungaro/coinwagon
